{
  "id": "w19d5",
  "week": 19,
  "day": 5,
  "title": "Mental Verbs with Abstractions",
  "goal": "Review which mental verbs take which abstractions.",
  "time": "15 minutes",
  "sections": [
    {
      "type": "warmup",
      "content": "<h2>Warm-up (2-3 min)</h2>\n<p>All 8 vocabulary words:</p>\n<pre><code>fail → ?       interrupt → ?\nbegin → ?      prevent → ?\nend → ?        recur → ?\nstop → ?       repeat → ?\n</code></pre>\n<p>(Answers: <code>fliba</code>, <code>dicra</code>, <code>cfari</code>, <code>fanta</code>, <code>fanmo</code>, <code>krefu</code>, <code>sisti</code>, <code>rapli</code>)</p>\n"
    },
    {
      "type": "material",
      "content": "<h2>New Material (5-7 min)</h2>\n<h3>Mental Verbs and Their Abstractions</h3>\n<table>\n<thead>\n<tr>\n<th>Verb</th>\n<th>Meaning</th>\n<th>Takes</th>\n<th>Example</th>\n</tr>\n</thead>\n<tbody><tr>\n<td><code>djuno</code></td>\n<td>know</td>\n<td>du&#39;u</td>\n<td><code>mi djuno lo du&#39;u do klama</code></td>\n</tr>\n<tr>\n<td><code>jimpe</code></td>\n<td>understand</td>\n<td>du&#39;u</td>\n<td><code>mi jimpe lo du&#39;u ti xamgu</code></td>\n</tr>\n<tr>\n<td><code>djica</code></td>\n<td>want</td>\n<td>nu</td>\n<td><code>mi djica lo nu citka</code></td>\n</tr>\n<tr>\n<td><code>pacna</code></td>\n<td>hope</td>\n<td>nu</td>\n<td><code>mi pacna lo nu do snada</code></td>\n</tr>\n<tr>\n<td><code>terpa</code></td>\n<td>fear</td>\n<td>nu</td>\n<td><code>mi terpa lo nu fliba</code></td>\n</tr>\n<tr>\n<td><code>nelci</code></td>\n<td>like</td>\n<td>nu/ka</td>\n<td><code>mi nelci lo ka cadzu</code></td>\n</tr>\n<tr>\n<td><code>cfari</code></td>\n<td>begin</td>\n<td>nu</td>\n<td><code>mi cfari lo nu gunka</code></td>\n</tr>\n<tr>\n<td><code>sisti</code></td>\n<td>stop</td>\n<td>nu</td>\n<td><code>mi sisti lo nu tavla</code></td>\n</tr>\n<tr>\n<td><code>troci</code></td>\n<td>try</td>\n<td>nu</td>\n<td><code>mi troci lo nu snada</code></td>\n</tr>\n<tr>\n<td><code>snada</code></td>\n<td>succeed</td>\n<td>nu</td>\n<td><code>mi snada lo nu klama</code></td>\n</tr>\n</tbody></table>\n<h3>Pattern: du&#39;u for Facts, nu for Events</h3>\n<p><strong>du&#39;u</strong> — verbs about knowing, believing, asserting:</p>\n<ul>\n<li>djuno, jimpe, xusra, tugni, natfe</li>\n</ul>\n<p><strong>nu</strong> — verbs about actions, desires, attempts:</p>\n<ul>\n<li>djica, pacna, terpa, cfari, sisti, troci, snada</li>\n</ul>\n<h3>Examples</h3>\n<pre><code>mi djuno lo du&#39;u do prami mi\n</code></pre>\n<p>I know that you love me.</p>\n<pre><code>mi djica lo nu do prami mi\n</code></pre>\n<p>I want you to love me.</p>\n<pre><code>mi pacna lo nu mi snada lo nu cilre\n</code></pre>\n<p>I hope I succeed in learning.</p>\n<h3>Key Point</h3>\n<blockquote>\n<p>Use du&#39;u with knowledge verbs, nu with action/desire verbs.</p>\n</blockquote>\n",
      "title": "New Material (5-7 min)"
    },
    {
      "type": "practice",
      "content": "<h2>Practice (4-5 min)</h2>\n<h3>Exercise 1: Match Verb to Abstractor</h3>\n<p>Fill in du&#39;u or nu:</p>\n<ol>\n<li><code>mi djuno lo ___ do klama</code></li>\n<li><code>mi djica lo ___ citka</code></li>\n<li><code>mi jimpe lo ___ ti vajni</code></li>\n<li><code>mi terpa lo ___ fliba</code></li>\n</ol>\n<details>\n<summary>Answers</summary>\n\n<ol>\n<li>du&#39;u (know)</li>\n<li>nu (want)</li>\n<li>du&#39;u (understand)</li>\n<li>nu (fear)</li>\n</ol>\n</details>\n\n<h3>Exercise 2: Translate</h3>\n<p>Translate:</p>\n<ol>\n<li>I know you work.</li>\n<li>I want to sleep.</li>\n<li>I hope you understand.</li>\n<li>I try to succeed.</li>\n</ol>\n<details>\n<summary>Answers</summary>\n\n<ol>\n<li><code>mi djuno lo du&#39;u do gunka</code></li>\n<li><code>mi djica lo nu sipna</code></li>\n<li><code>mi pacna lo nu do jimpe</code></li>\n<li><code>mi troci lo nu snada</code></li>\n</ol>\n</details>\n\n<h3>Exercise 3: Complex Sentences</h3>\n<p>Translate:</p>\n<ol>\n<li>I know you want to go.</li>\n<li>I hope I begin to understand.</li>\n<li>I fear I will fail to try.</li>\n</ol>\n<details>\n<summary>Answers</summary>\n\n<ol>\n<li><code>mi djuno lo du&#39;u do djica lo nu klama</code></li>\n<li><code>mi pacna lo nu mi cfari lo nu jimpe</code></li>\n<li><code>mi terpa lo nu mi fliba lo nu troci</code></li>\n</ol>\n</details>",
      "exercises": [
        {
          "number": 1,
          "type": "matching",
          "items": [
            {
              "text": "`mi djuno lo ___ do klama`",
              "answer": "du'u (know)"
            },
            {
              "text": "`mi djica lo ___ citka`",
              "answer": "nu (want)"
            },
            {
              "text": "`mi jimpe lo ___ ti vajni`",
              "answer": "du'u (understand)"
            },
            {
              "text": "`mi terpa lo ___ fliba`",
              "answer": "nu (fear)"
            }
          ]
        },
        {
          "number": 2,
          "type": "translate",
          "items": [
            {
              "text": "I know you work.",
              "answer": "`mi djuno lo du'u do gunka`"
            },
            {
              "text": "I want to sleep.",
              "answer": "`mi djica lo nu sipna`"
            },
            {
              "text": "I hope you understand.",
              "answer": "`mi pacna lo nu do jimpe`"
            },
            {
              "text": "I try to succeed.",
              "answer": "`mi troci lo nu snada`"
            }
          ]
        },
        {
          "number": 3,
          "type": "complex-sentences",
          "items": [
            {
              "text": "I know you want to go.",
              "answer": "`mi djuno lo du'u do djica lo nu klama`"
            },
            {
              "text": "I hope I begin to understand.",
              "answer": "`mi pacna lo nu mi cfari lo nu jimpe`"
            },
            {
              "text": "I fear I will fail to try.",
              "answer": "`mi terpa lo nu mi fliba lo nu troci`"
            }
          ]
        }
      ]
    },
    {
      "type": "conversation",
      "content": "<h2>Conversation Challenge (1-2 min)</h2>\n<p><strong>Say aloud:</strong></p>\n<ol>\n<li>&quot;I know you go.&quot; → <code>mi djuno lo du&#39;u do klama</code></li>\n<li>&quot;I want to work.&quot; → <code>mi djica lo nu gunka</code></li>\n<li>&quot;I try to succeed.&quot; → <code>mi troci lo nu snada</code></li>\n</ol>\n"
    },
    {
      "type": "other",
      "content": "<h2>Today&#39;s Review</h2>\n<p><strong>Abstractor selection:</strong></p>\n<table>\n<thead>\n<tr>\n<th>Verb Type</th>\n<th>Abstractor</th>\n</tr>\n</thead>\n<tbody><tr>\n<td>Know, understand, believe</td>\n<td>du&#39;u</td>\n</tr>\n<tr>\n<td>Want, hope, fear, try</td>\n<td>nu</td>\n</tr>\n<tr>\n<td>Like (as quality)</td>\n<td>ka</td>\n</tr>\n</tbody></table>\n"
    },
    {
      "type": "summary",
      "content": "<h2>Summary</h2>\n<blockquote>\n<p>You reviewed which mental verbs take which abstractions. Knowledge verbs use du&#39;u; action/desire verbs use nu.</p>\n</blockquote>\n<p><strong>Tomorrow preview:</strong> Conversation practice with abstractions.</p>\n",
      "tomorrow": "Conversation practice with abstractions."
    }
  ]
}